microauth_fastapi/__init__.py
microauth_fastapi/auth.py
microauth_fastapi/config.py
microauth_fastapi/dependencies.py
microauth_fastapi/exceptions.py
microauth_fastapi/jwks.py
microauth_fastapi/schemas.py
microauth_fastapi-1.0.0.dist-info/METADATA
microauth_fastapi-1.0.0.dist-info/WHEEL
microauth_fastapi-1.0.0.dist-info/top_level.txt
microauth_fastapi-1.0.0.dist-info/RECORD
