Metadata-Version: 2.4
Name: microauth-fastapi
Version: 1.0.0
Summary: FastAPI JWT verification integration for MicroAuth IdP
Home-page: https://github.com/microauth-org/microauth-fastapi
Author: MicroAuth
Author-email: support@microauth.com
Classifier: Programming Language :: Python :: 3.13
Classifier: Framework :: FastAPI
Classifier: License :: OSI Approved :: MIT License
Requires-Dist: fastapi
Requires-Dist: httpx
Requires-Dist: python-jose[cryptography]
Requires-Dist: pydantic
Requires-Dist: structlog
Dynamic: author
Dynamic: author-email
Dynamic: classifier
Dynamic: home-page
Dynamic: requires-dist
Dynamic: summary
